<annotation>
	<folder>JPEGImages</folder>
	<filename>00021.jpg</filename>
	<path>F:\darknet-master\scripts\VOCdevkit\VOC2019\JPEGImages\00021.jpg</path>
	<source>
		<database>Unknown</database>
	</source>
	<size>
		<width>1080</width>
		<height>810</height>
		<depth>3</depth>
	</size>
	<segmented>0</segmented>
	<object>
		<name>sqrt</name>
		<pose>Unspecified</pose>
		<truncated>0</truncated>
		<difficult>0</difficult>
		<bndbox>
			<xmin>509</xmin>
			<ymin>278</ymin>
			<xmax>676</xmax>
			<ymax>398</ymax>
		</bndbox>
	</object>
	<object>
		<name>sqrt</name>
		<pose>Unspecified</pose>
		<truncated>0</truncated>
		<difficult>0</difficult>
		<bndbox>
			<xmin>236</xmin>
			<ymin>275</ymin>
			<xmax>409</xmax>
			<ymax>398</ymax>
		</bndbox>
	</object>
</annotation>
